gekitchen/__init__.py
gekitchen/async_login_flow.py
gekitchen/const.py
gekitchen/erd_types.py
gekitchen/erd_utils.py
gekitchen/exc.py
gekitchen/ge_appliance.py
gekitchen/login_flow.py
gekitchen/clients/__init__.py
gekitchen/clients/base_client.py
gekitchen/clients/websocket_client.py
gekitchen/clients/xmpp_client.py
gekitchen/erd_constants/__init__.py
gekitchen/erd_constants/erd_codes.py
gekitchen/erd_constants/erd_constants.py
gekitchen-0.2.20.dist-info/LICENSE
gekitchen-0.2.20.dist-info/METADATA
gekitchen-0.2.20.dist-info/WHEEL
gekitchen-0.2.20.dist-info/top_level.txt
gekitchen-0.2.20.dist-info/RECORD
