Metadata-Version: 2.1
Name: gekitchen
Version: 0.2.20
Summary: Python SDK for GE Kitchen Appliances
Home-page: https://github.com/ajmarks/gekitchen
Author: Andrew Marks
Author-email: ajmarks@gmail.com
License: MIT
Platform: UNKNOWN
Classifier: License :: OSI Approved :: MIT License
Classifier: Programming Language :: Python :: 3
Classifier: Programming Language :: Python :: 3.7
Requires-Dist: aiohttp
Requires-Dist: bidict
Requires-Dist: requests
Requires-Dist: websockets
Provides-Extra: xmpp
Requires-Dist: slixmpp (==1.5.2) ; extra == 'xmpp'
